{
  "福容大飯店": [],
  "台北W飯店": ["台北W Hotel", "臺北W飯店", "臺北W Hotel"],
  "香格里拉台北遠東國際大飯店": ["遠東香格里拉"],
  "美麗信花園酒店": [],
  "圓山大飯店": ["圓山飯店"],
  "老爺大酒店": [],
  "高雄凱悅酒店": [],
  "凱悅渡假酒店": [],
  "台北六福萬怡酒店": ["六福萬怡"],
  "亞都麗緻大飯店": ["亞都麗緻"],
  "晶華酒店": ["晶華", "晶華飯店"],
  "維多麗亞酒店": [],
  "台北美福大飯店": ["美福大飯店"],
  "台北寒舍喜來登大飯店": ["喜來登大飯店"],
  "台北寒舍艾美酒店": ["寒舍艾美", "寒舍艾美酒店"],
  "台北君悅酒店": ["君悅大飯店"],
  "北投麗禧溫泉酒店": [],
  "大地酒店": [],
  "台北萬豪酒店": [],
  "台北大倉久和大飯店": ["大倉久和大飯店"],
  "君品酒店": [],
  "台北富信大飯店": [],
  "板橋凱撒大飯店": [],
  "尊爵天際大飯店": [],
  "古華花園飯店": [],
  "尊爵大飯店": [],
  "曼谷凱悅愛侶灣飯店": [],
  "愛侶灣君悅飯店": [],
  "和逸飯店": [],
  "阿思瑪麗景大飯店": [],
  "台北喜來登大飯店": [],
  "高雄漢來飯店": [],
  "棒棒積木飯店": [],
  "綠舞觀光飯店": [],
  "台北諾富特華航桃園機場飯店": [],
  "新竹國賓大飯店": [],
  "新竹豐邑喜來登大飯店": [],
  "清新溫泉度假飯店": [],
  "永豐棧酒店": [],
  "裕元花園酒店": [],
  "台中日月千禧酒店": [],
  "長榮桂冠酒店（台中）": [],
  "台中金典酒店": [],
  "涵碧樓大飯店": [],
  "日月潭雲品溫泉酒店": ["雲品溫泉酒店"],
  "溪頭米堤飯店": [],
  "劍湖山渡假大飯店": [],
  "耐斯王子大飯店": [],
  "新悅花園酒店": [],
  "長榮文苑酒店（嘉義）": [],
  "阿里山英迪格酒店": [],
  "台南大員皇冠假日酒店": [],
  "香格里拉台南遠東國際大飯店": [],
  "義大皇家酒店": [],
  "寒軒國際大飯店": [],
  "漢來大飯店": [],
  "高雄福華大飯店": [],
  "水京棧國際酒店": [],
  "高雄洲際酒店": [],
  "晶英國際行館": [],
  "墾丁夏都沙灘酒店": [],
  "墾丁凱撒大飯店": [],
  "長榮鳳凰酒店(礁溪)": [],
  "蘭城晶英酒店": [],
  "美侖大飯店": [],
  "太魯閣晶英酒店": [],
  "遠雄悅來大飯店": [],
  "花蓮理想大地渡假飯店": [],
  "瑞穗天合國際觀光酒店": [],
  "花蓮潔西艾美酒店": [],
  "知本老爺酒店": [],
  "娜路彎大酒店": [],
  "日暉國際渡假村": [],
  "台東桂田喜來登酒店": [],
  "澎湖福朋喜來登酒店": [],
  "大倉日航酒店": [],
  "長榮桂冠酒店": [],
  "夏都酒店集團": ["夏都酒店"],
  "老爺酒店集團": ["老爺酒店"],
  "桂田喜來登酒店": ["桂田酒店", "喜來登酒店"],
  "國泰萬怡酒店": [],
  "力麗威斯汀度假酒店": [],
  "承億酒店": [],
  "長榮酒店": [],
  "長榮巴黎桂冠酒店": [],
  "台中林酒店": [],
  "三亞天域度假酒店": [],
  "百世多麗酒店": [],
  "金湖飯店": [],
  "達洛鞍休閒民宿": [],
  "潔西艾美渡假酒店": []
}
