{
    "大衛": {
        "全名": [
            "大衛"
        ],
        "職銜": [
            "亨廷頓伯爵"
        ],
        "生日": [],
        "出生地": [
            "亨廷登",
            "英格蘭王國"
        ],
        "忌日": [
            "1219年6月17日"
        ],
        "死亡地": [
            "蘇格蘭王國傑德堡"
        ],
        "配偶": [],
        "父母": []
    },
    "陸地": {
        "全名": [
            "陸地"
        ],
        "出生地": [
            "扶綏",
            "廣西"
        ],
        "忌日": [
            "2010年8月7日"
        ],
        "死亡地": [
            "廣西南寧"
        ],
        "職銜": [
            "小說家"
        ],
        "國籍": []
    },
    "藝人": {
        "生日": [
            "1993/09/16"
        ],
        "出生地": [
            "密蘇里州",
            "聖路易斯"
        ],
        "職銜": [
            "{{hlist|音樂製作人|DJ|詞曲作家}}"
        ]
    },
    "高興": {
        "全名": [
            "高興"
        ],
        "生日": [],
        "出生地": [
            "中國",
            "新疆維吾爾自治區",
            "烏魯木齊"
        ],
        "教育背景": [
            "新疆師範大學"
        ]
    },
    "喬治": {
        "全名": [
            "喬治·帕裡西{{nobel icon}}"
        ],
        "生日": [
            "1948/8/04"
        ],
        "出生地": [
            "羅馬"
        ],
        "國籍": [],
        "教育背景": [
            "羅馬大學"
        ],
        "獎項": [
            "玻爾茲曼獎章&lt;br&gt;狄拉克獎章&lt;br&gt;恩里科·費米獎&lt;br&gt;丹尼·海涅曼數學物理獎&lt;br&gt;{{link-it|諾尼諾獎|Premio Nonino}}&lt;br&gt;微軟獎&lt;br&gt;拉格朗日獎&lt;br&gt;馬克斯·普朗克獎章&lt;br&gt;{{link-de|高能和粒子物理獎|High Energy and Particle Physics Prize}}&lt;br&gt;拉斯·昂薩格獎&lt;br/&gt;諾貝爾物理學獎"
        ]
    },
    "露西": {
        "全名": [
            "露西 • 格雷"
        ],
        "出生地": []
    },
    "哥倫": {
        "全名": [
            "哥倫 &lt;br&gt; Goran Stankovski"
        ],
        "生日": [
            "1976/11/20"
        ],
        "出生地": [
            "史高比耶",
            "南斯拉夫"
        ]
    }
}