{
  "臺北監獄": ["台北監獄"],
  "桃園監獄": [],
  "桃園女子監獄": [],
  "新竹監獄": [],
  "臺中監獄": ["台中監獄"],
  "臺中女子監獄": ["台中女子監獄"],
  "彰化監獄": [],
  "雲林監獄": [],
  "雲林第二監獄": [],
  "嘉義監獄": [],
  "臺南監獄": ["台南監獄"],
  "臺南第二監獄": ["台南第二監獄"],
  "高雄監獄": [],
  "高雄第二監獄": [],
  "高雄女子監獄": [],
  "屏東監獄": [],
  "基隆監獄": [],
  "宜蘭監獄": [],
  "花蓮監獄": [],
  "臺東監獄": ["台東監獄"],
  "澎湖監獄": [],
  "金門監獄": [],
  "綠島監獄": [],
  "八德外役監獄": [],
  "臺中監獄外役分監": ["台中監獄外役分監"],
  "臺中女子監獄外役分監": ["台中女子監獄外役分監"],
  "明德外役監獄": [],
  "屏東監獄外役分監": [],
  "自強外役監獄": [],
  "臺東監獄武陵外役分監": ["台東監獄武陵外役分監"],
  "基隆看守所": [],
  "臺北看守所": ["台北看守所"],
  "臺北女子看守所": ["台北女子看守所"],
  "新竹看守所": [],
  "苗栗看守所": [],
  "臺中看守所": ["台中看守所"],
  "彰化看守所": [],
  "南投看守所": [],
  "嘉義看守所": [],
  "臺南看守所": ["台南看守所"],
  "屏東看守所": [],
  "花蓮看守所": [],
  "桃園看守所": [],
  "雲林看守所": [],
  "高雄看守所": [],
  "宜蘭看守所": [],
  "臺東看守所": ["台東看守所"],
  "澎湖看守所": [],
  "金門看守所": [],
  "連江看守所": [],
  "泰源技能訓練所": [],
  "東成技能訓練所": [],
  "岩灣技能訓練所": [],
  "臺北少年觀護所": ["台北少年觀護所"],
  "臺南少年觀護所": ["台南少年觀護所"],
  "新店戒治所": [],
  "臺中戒治所": ["台中戒治所"],
  "高雄戒治所": [],
  "臺東戒治所": ["台東戒治所"]
}
